EETQ.cpython-310-x86_64-linux-gnu.so
eetq/__init__.py
eetq/models/__init__.py
eetq/models/_config.py
eetq/models/auto.py
eetq/models/base.py
eetq/models/llama.py
eetq/modules/__init__.py
eetq/modules/llama_modules.py
eetq/modules/qlinear.py
eetq/utils/__init__.py
eetq/utils/accelerator.py
eetq/utils/base.py
eetq/utils/mapping.py
eetq/utils/quantizer.py
EETQ-1.0.0.dist-info/METADATA
EETQ-1.0.0.dist-info/WHEEL
EETQ-1.0.0.dist-info/top_level.txt
EETQ-1.0.0.dist-info/RECORD
