Metadata-Version: 2.1
Name: EETQ
Version: 1.0.0
Summary: Easy and efficient quantization for transformer
Home-page: https://github.com/NetEase-FuXi/EETQ
Author: zhaosida, zhuangzhong
Author-email: zhaosida@corp.netease.com, zhuangzhong@corp.netease.com
Requires-Python: >=3.7
Requires-Dist: torch
Requires-Dist: einops
Requires-Dist: packaging
Requires-Dist: ninja
